SQLAlchemy_ImageAttach-1.1.0.dist-info/DESCRIPTION.rst
SQLAlchemy_ImageAttach-1.1.0.dist-info/METADATA
SQLAlchemy_ImageAttach-1.1.0.dist-info/RECORD
SQLAlchemy_ImageAttach-1.1.0.dist-info/WHEEL
SQLAlchemy_ImageAttach-1.1.0.dist-info/metadata.json
SQLAlchemy_ImageAttach-1.1.0.dist-info/top_level.txt
sqlalchemy_imageattach/__init__.py
sqlalchemy_imageattach/context.py
sqlalchemy_imageattach/entity.py
sqlalchemy_imageattach/file.py
sqlalchemy_imageattach/migration.py
sqlalchemy_imageattach/store.py
sqlalchemy_imageattach/util.py
sqlalchemy_imageattach/version.py
sqlalchemy_imageattach/stores/__init__.py
sqlalchemy_imageattach/stores/fs.py
sqlalchemy_imageattach/stores/s3.py
