Metadata-Version: 1.1
Name: SQLAlchemy-ImageAttach
Version: 1.1.0
Summary: SQLAlchemy extension for attaching images to entity objects
Home-page: https://github.com/dahlia/sqlalchemy-imageattach
Author: Hong Minhee
Author-email: hong.minhee@gmail.com
License: MIT License
Platform: UNKNOWN
Classifier: Development Status :: 4 - Beta
Classifier: Intended Audience :: Developers
Classifier: License :: OSI Approved :: MIT License
Classifier: Operating System :: OS Independent
Classifier: Programming Language :: Python :: 2.7
Classifier: Programming Language :: Python :: 3
Classifier: Programming Language :: Python :: 3.3
Classifier: Programming Language :: Python :: 3.4
Classifier: Programming Language :: Python :: 3.5
Classifier: Programming Language :: Python :: 3.6
Classifier: Programming Language :: Python :: Implementation :: CPython
Classifier: Programming Language :: Python :: Implementation :: PyPy
Classifier: Programming Language :: Python :: Implementation :: Stackless
Classifier: Topic :: Database :: Front-Ends
Classifier: Topic :: Multimedia :: Graphics
